wexample_filestate_git-0.0.59.dist-info/METADATA
wexample_filestate_git-0.0.59.dist-info/WHEEL
wexample_filestate_git-0.0.59.dist-info/entry_points.txt
wexample_filestate_git-0.0.59.dist-info/licenses/LICENSE
wexample_filestate_git/__init__.py
wexample_filestate_git/__pycache__/__init__.py
wexample_filestate_git/config_value/__init__.py
wexample_filestate_git/config_value/__pycache__/__init__.py
wexample_filestate_git/config_value/git_config_value.py
wexample_filestate_git/config_value/remote_config_value.py
wexample_filestate_git/operation/__init__.py
wexample_filestate_git/operation/__pycache__/__init__.py
wexample_filestate_git/operation/abstract_git_operation.py
wexample_filestate_git/operation/git_create_branch_operation.py
wexample_filestate_git/operation/git_init_operation.py
wexample_filestate_git/operation/git_remote_add_operation.py
wexample_filestate_git/operation/git_remote_create_operation.py
wexample_filestate_git/option/__init__.py
wexample_filestate_git/option/__pycache__/__init__.py
wexample_filestate_git/option/_git/__init__.py
wexample_filestate_git/option/_git/__pycache__/__init__.py
wexample_filestate_git/option/_git/create_remote_option.py
wexample_filestate_git/option/_git/main_branch_option.py
wexample_filestate_git/option/_git/remote_item_option.py
wexample_filestate_git/option/_git/remote_option.py
wexample_filestate_git/option/_git/type_option.py
wexample_filestate_git/option/_git/url_option.py
wexample_filestate_git/option/git_option.py
wexample_filestate_git/options_provider/__init__.py
wexample_filestate_git/options_provider/__pycache__/__init__.py
wexample_filestate_git/options_provider/git_options_provider.py
wexample_filestate_git/py.typed
wexample_filestate_git/remote/__init__.py
wexample_filestate_git/remote/__pycache__/__init__.py
wexample_filestate_git/remote/abstract_remote.py
wexample_filestate_git/remote/github_remote.py
wexample_filestate_git/remote/gitlab_remote.py
wexample_filestate_git/test/__init__.py
wexample_filestate_git/test/__pycache__/__init__.py
wexample_filestate_git/test/mixin/__init__.py
wexample_filestate_git/test/mixin/__pycache__/__init__.py
wexample_filestate_git/test/mixin/test_git_state_manager_mixin.py
wexample_filestate_git-0.0.59.dist-info/RECORD
