Metadata-Version: 2.1
Name: wexample-filestate-git
Version: 0.0.59
Summary: An extension for "filestate" package, which adds GIT management operations.
Author-Email: weeger <contact@wexample.com>
License: MIT
Classifier: Programming Language :: Python :: 3
Classifier: License :: OSI Approved :: MIT License
Classifier: Operating System :: OS Independent
Project-URL: homepage, https://github.com/wexample/python-filestate-git
Requires-Python: >=3.10
Requires-Dist: attrs>=23.1.0
Requires-Dist: cattrs>=23.1.0
Requires-Dist: requests
Requires-Dist: wexample-api==0.0.83
Requires-Dist: wexample-filestate==0.0.74
Requires-Dist: wexample-helpers-git==0.0.96
Provides-Extra: dev
Requires-Dist: pytest; extra == "dev"
Requires-Dist: pytest-cov; extra == "dev"
